Metadata-Version: 2.4
Name: sopel_modules.urban
Version: 1.2.2
Summary: Urban Dictionary module for Sopel
Home-page: http://github.com/rustybower/sopel-urban
Author: Rusty Bower
Author-email: rusty@rustybower.com
License: MIT License
License-File: LICENSE
Requires-Dist: sopel<8,>=6.6.2
Dynamic: author
Dynamic: author-email
Dynamic: description
Dynamic: description-content-type
Dynamic: home-page
Dynamic: license
Dynamic: license-file
Dynamic: requires-dist
Dynamic: summary
